MESSENGERuvvs/MESSENGER_summary_table.py
MESSENGERuvvs/MESSENGERdata.py
MESSENGERuvvs/MESSENGERdata_db.py
MESSENGERuvvs/MESSENGERdata_db_version.py
MESSENGERuvvs/MESSENGERview.py
MESSENGERuvvs/MESSENGERviewer.py
MESSENGERuvvs/__init__.py
MESSENGERuvvs/database_setup.py
MESSENGERuvvs/databasebackups.py
MESSENGERuvvs/initialize_MESSENGERdata.py
MESSENGERuvvs/plot_methods.py
MESSENGERuvvs/version.py
MESSENGERuvvs/data/MESSENGER.orbitdata.pkl
MESSENGERuvvs/data/MES_merc_year.pkl
MESSENGERuvvs/data/bokeh.yml
MESSENGERuvvs/data/modeltest.pkl
MESSENGERuvvs/tests/__init__.py
MESSENGERuvvs/tests/test_MESSENGERdata.py
MESSENGERuvvs/tests/test_database_connect.py
MESSENGERuvvs-1.11.6.dist-info/LICENSE.rst
MESSENGERuvvs-1.11.6.dist-info/METADATA
MESSENGERuvvs-1.11.6.dist-info/WHEEL
MESSENGERuvvs-1.11.6.dist-info/top_level.txt
MESSENGERuvvs-1.11.6.dist-info/RECORD
