Metadata-Version: 2.1
Name: MESSENGERuvvs
Version: 1.11.6
Summary: Routines for working with MESSENGER UVVS data
Home-page: https://github.com/mburger-stsci/MESSENGERuvvs
Author: Matthew Burger
Author-email: mburger@stsci.edu
License: BSD 3-Clause
Requires-Python: >=3.6
License-File: LICENSE.rst
Requires-Dist: scipy
Requires-Dist: numpy
Requires-Dist: astropy
Requires-Dist: pandas
Requires-Dist: psycopg2
Requires-Dist: bokeh
Requires-Dist: nexoclom
